InforeWss/__init__.py
InforeWss/main.py
InforeWss-1.0.1.dist-info/LICENSE.txt
InforeWss-1.0.1.dist-info/METADATA
InforeWss-1.0.1.dist-info/WHEEL
InforeWss-1.0.1.dist-info/top_level.txt
InforeWss-1.0.1.dist-info/RECORD
